pyiptv/__init__.py
pyiptv/cache_manager.py
pyiptv/m3u_parser.py
pyiptv/main.py
pyiptv/playlist_manager.py
pyiptv/qmedia_player.py
pyiptv/settings_manager.py
pyiptv/ui/__init__.py
pyiptv/ui/main_window.py
pyiptv/ui/playlist_manager_window.py
pyiptv/ui/themes.py
pyiptv/ui/url_download_worker.py
pyiptv/ui/components/__init__.py
pyiptv/ui/components/audio_track_selector.py
pyiptv/ui/components/category_list.py
pyiptv/ui/components/enhanced_controls.py
pyiptv/ui/components/metadata_display.py
pyiptv/ui/components/simplified_operations.py
pyiptv/ui/components/unified_status_system.py
pyiptv/ui/components/video_placeholder.py
pyiptv/ui/components/virtualized_channel_list.py
pyiptv/ui/images/logo.png
pyiptv/ui/images/logo_old.png
pyiptv-1.0.0.dist-info/licenses/LICENSE
pyiptv-1.0.0.dist-info/METADATA
pyiptv-1.0.0.dist-info/WHEEL
pyiptv-1.0.0.dist-info/entry_points.txt
pyiptv-1.0.0.dist-info/top_level.txt
pyiptv-1.0.0.dist-info/RECORD
