Metadata-Version: 2.4
Name: pyiptv
Version: 1.0.0
Summary: A modern IPTV player built with PySide6
Author-email: David Markey <david@dmarkey.com>
Maintainer-email: David Markey <david@dmarkey.com>
License-Expression: MIT
Project-URL: Homepage, https://github.com/dmarkey/PyIPTV
Project-URL: Repository, https://github.com/dmarkey/PyIPTV
Project-URL: Issues, https://github.com/dmarkey/PyIPTV/issues
Project-URL: Documentation, https://github.com/dmarkey/PyIPTV#readme
Keywords: iptv,player,streaming,media,m3u,pyside6,qt
Classifier: Development Status :: 4 - Beta
Classifier: Intended Audience :: End Users/Desktop
Classifier: Operating System :: OS Independent
Classifier: Programming Language :: Python :: 3
Classifier: Programming Language :: Python :: 3.8
Classifier: Programming Language :: Python :: 3.9
Classifier: Programming Language :: Python :: 3.10
Classifier: Programming Language :: Python :: 3.11
Classifier: Programming Language :: Python :: 3.12
Classifier: Topic :: Multimedia :: Video :: Display
Classifier: Environment :: X11 Applications :: Qt
Requires-Python: >=3.8
License-File: LICENSE
Requires-Dist: PySide6>=6.5.0
Requires-Dist: requests>=2.25.0
Provides-Extra: dev
Requires-Dist: pytest>=6.0; extra == "dev"
Requires-Dist: black>=22.0; extra == "dev"
Requires-Dist: isort>=5.0; extra == "dev"
Requires-Dist: flake8>=4.0; extra == "dev"
Dynamic: license-file
